{"login": {"ping": 19.52981948852539}, "game": {"state": -1, "servers": [{"state": -1, "name": "mabius2", "channels": [{"state": -1, "name": "HCh", "ping": 19.457340240478516, "stress": 0, "event": false}, {"state": -1, "name": "Ch4", "ping": 17.964839935302734, "stress": 0, "event": false}, {"state": -1, "name": "Ch2", "ping": 18.539905548095703, "stress": 0, "event": false}, {"state": -1, "name": "Ch7", "ping": 19.161224365234375, "stress": 0, "event": false}, {"state": -1, "name": "Ch6", "ping": 19.309282302856445, "stress": 0, "event": false}, {"state": -1, "name": "Ch1", "ping": 19.304275512695312, "stress": 0, "event": false}, {"state": -1, "name": "Ch3", "ping": 19.63210105895996, "stress": 0, "event": false}, {"state": -1, "name": "Ch5", "ping": 19.994258880615234, "stress": 0, "event": false}], "stress": 0, "event": false}, {"state": -1, "name": "mabius4", "channels": [{"state": -1, "name": "HCh", "ping": 20.131826400756836, "stress": 0, "event": false}, {"state": -1, "name": "Ch4", "ping": 18.413543701171875, "stress": 0, "event": false}, {"state": -1, "name": "Ch2", "ping": 19.860029220581055, "stress": 0, "event": false}, {"state": -1, "name": "Ch7", "ping": 18.82457733154297, "stress": 0, "event": false}, {"state": -1, "name": "Ch6", "ping": 18.643856048583984, "stress": 0, "event": false}, {"state": -1, "name": "Ch1", "ping": 19.99640464782715, "stress": 0, "event": false}, {"state": -1, "name": "Ch3", "ping": 18.280506134033203, "stress": 0, "event": false}, {"state": -1, "name": "Ch5", "ping": 18.06020736694336, "stress": 0, "event": false}], "stress": 0, "event": false}, {"state": -1, "name": "mabius1", "channels": [{"state": -1, "name": "HCh", "ping": 20.15542984008789, "stress": 0, "event": false}, {"state": -1, "name": "Ch4", "ping": 19.658565521240234, "stress": 0, "event": false}, {"state": -1, "name": "Ch2", "ping": 19.424915313720703, "stress": 0, "event": false}, {"state": -1, "name": "Ch7", "ping": 20.066261291503906, "stress": 0, "event": false}, {"state": -1, "name": "Ch6", "ping": 19.870519638061523, "stress": 0, "event": false}, {"state": -1, "name": "Ch1", "ping": 20.30491828918457, "stress": 0, "event": false}, {"state": -1, "name": "Ch3", "ping": 19.601106643676758, "stress": 0, "event": false}, {"state": -1, "name": "Ch5", "ping": 18.07427406311035, "stress": 0, "event": false}], "stress": 0, "event": false}, {"state": -1, "name": "mabius3", "channels": [{"state": -1, "name": "HCh", "ping": 20.010948181152344, "stress": 0, "event": false}, {"state": -1, "name": "Ch4", "ping": 19.1497802734375, "stress": 0, "event": false}, {"state": -1, "name": "Ch2", "ping": 18.84627342224121, "stress": 0, "event": false}, {"state": -1, "name": "Ch7", "ping": 20.029306411743164, "stress": 0, "event": false}, {"state": -1, "name": "Ch6", "ping": 18.389463424682617, "stress": 0, "event": false}, {"state": -1, "name": "Ch1", "ping": 19.45209503173828, "stress": 0, "event": false}, {"state": -1, "name": "Ch3", "ping": 19.954204559326172, "stress": 0, "event": false}, {"state": -1, "name": "Ch5", "ping": 19.098997116088867, "stress": 0, "event": false}], "stress": 0, "event": false}], "stress": 0, "event": false}, "chat": {"ping": 18.901586532592773}, "updated": "2017-03-02T14:19:33.255067", "type": "ping", "website": {"ping": 22.115707397460938}}